{"type": "FeatureCollection", "metadata": {"gemeente": "Schiermonnikoog", "slug": "schiermonnikoog", "province": "Friesland", "generated_at": "2025-10-24T08:15:39.171590Z", "total_points": 2, "providers": ["DHL", "DPD"], "bounds": null, "note": "No pakketpunten data available for this municipality"}, "features": [{"type": "Feature", "geometry": {"type": "Point", "coordinates": [6.156630516052246, 53.478092193603516]}, "properties": {"type": "pakketpunt", "locatieNaam": "Kolstein lifestyle & boeken", "straatNaam": "Middenstreek", "straatNr": "38", "latitude": 53.478092193603516, "longitude": 6.156630516052246, "vervoerder": "DHL", "puntType": "parcelShop", "bezettingsgraad": 0}}, {"type": "Feature", "geometry": {"type": "Point", "coordinates": [6.1575832, 53.4782568]}, "properties": {"type": "pakketpunt", "locatieNaam": "Boekhandel Kolstein", "straatNaam": "MIDDENSTREEK", "straatNr": "38", "latitude": 53.4782568, "longitude": 6.1575832, "vervoerder": "DPD", "puntType": "pickup_point", "bezettingsgraad": 0}}]}